threa/__init__.py
threa/collection.py
threa/py.typed
threa/runnable.py
threa/thread.py
threa/wrapper.py
threa-1.9.1.dist-info/LICENSE
threa-1.9.1.dist-info/METADATA
threa-1.9.1.dist-info/WHEEL
threa-1.9.1.dist-info/RECORD
