Metadata-Version: 2.1
Name: threa
Version: 1.9.1
Summary: 🧵 Better threads 🧵
Home-page: https://github.com/rec/threa
License: MIT
Author: Tom Ritchford
Author-email: tom@swirly.com
Requires-Python: >=3.8
Classifier: License :: OSI Approved :: MIT License
Classifier: Programming Language :: Python :: 3
Classifier: Programming Language :: Python :: 3.8
Classifier: Programming Language :: Python :: 3.9
Classifier: Programming Language :: Python :: 3.10
Classifier: Programming Language :: Python :: 3.11
Classifier: Programming Language :: Python :: 3.12
Requires-Dist: coverage (>=7.3.2,<8.0.0)
Project-URL: Repository, https://github.com/rec/threa
